MANIFEST.in
README.md
requirements-min-django.txt
requirements-test.txt
requirements.txt
setup.py
admin_steroids/__init__.py
admin_steroids/decorators.py
admin_steroids/email.py
admin_steroids/fields.py
admin_steroids/filters.py
admin_steroids/formatters.py
admin_steroids/managers.py
admin_steroids/models.py
admin_steroids/options.py
admin_steroids/queryset.py
admin_steroids/settings.py
admin_steroids/urls.py
admin_steroids/utils.py
admin_steroids/views.py
admin_steroids/widgets.py
admin_steroids/management/__init__.py
admin_steroids/management/commands/__init__.py
admin_steroids/management/commands/bulk_password_reset.py
admin_steroids/management/commands/createsuperuser_nice.py
admin_steroids/management/commands/delete_duplicate_record.py
admin_steroids/management/commands/force_logout.py
admin_steroids/management/commands/test_cache.py
admin_steroids/management/commands/test_mail.py
admin_steroids/static/admin_steroids/css/admin-overrides.css
admin_steroids/static/admin_steroids/js/custom.js
admin_steroids/static/admin_steroids/js/jquery-1.8.3.js
admin_steroids/static/admin_steroids/js/jquery-ui-1.9.2.custom.js
admin_steroids/static/admin_steroids/js/jquery.collapse-stacked-inlines.js
admin_steroids/static/admin_steroids/js/jquery.cookie.js
admin_steroids/static/admin_steroids/js/jquery.floatheader.js
admin_steroids/static/admin_steroids/js/jquery.inview.js
admin_steroids/templates/admin_steroids/ajax_filter.html
admin_steroids/templates/admin_steroids/base_site.html
admin_steroids/templates/admin_steroids/filter.html
admin_steroids/templates/admin_steroids/textinput_filter.html
admin_steroids/templatetags/__init__.py
admin_steroids/templatetags/admin_steroids.py
admin_steroids/tests/__init__.py
admin_steroids/tests/admin.py
admin_steroids/tests/manage.py
admin_steroids/tests/models.py
admin_steroids/tests/settings.py
admin_steroids/tests/tests.py
admin_steroids/tests/urls.py
django_admin_steroids.egg-info/PKG-INFO
django_admin_steroids.egg-info/SOURCES.txt
django_admin_steroids.egg-info/dependency_links.txt
django_admin_steroids.egg-info/not-zip-safe
django_admin_steroids.egg-info/requires.txt
django_admin_steroids.egg-info/top_level.txt