Metadata-Version: 2.1
Name: django-admin-steroids
Version: 1.0.37
Summary: Tweaks and tools to simplify Django admin.
Home-page: https://gitlab.com/chrisspen/django-admin-steroids
Author: Chris Spencer
Author-email: chrisspen@gmail.com
License: LGPL
Platform: UNKNOWN
Classifier: Environment :: Web Environment
Classifier: Intended Audience :: Developers
Classifier: License :: OSI Approved :: GNU Lesser General Public License v3 (LGPLv3)
Classifier: Operating System :: OS Independent
Classifier: Programming Language :: Python
Classifier: Framework :: Django
Classifier: Programming Language :: Python :: 3.7
Classifier: Programming Language :: Python :: 3.9
